{
  "apps": [
    {
      "name": "Blog",
      "iconValue": "images/icons/blog.png",
      "iconType": "image",
      "link": "https://substack.com/@commandrq",
      "external": true
    },
    {
      "name": "Social Media",
      "iconValue": "images/icons/tiktok.png",
      "iconType": "image",
      "link": "https://www.tiktok.com/@commandr_q",
      "external": true
    },
    {
      "name": "Dreamscape Drift",
      "iconValue": "images/icon/drift.png",
      "iconType": "image",
      "link": "drift.html",
      "external": false
    }
  ]
}
